base_service/__init__.py
base_service/database.py
base_service/models/__init__.py
base_service/models/base.py
base_service/utils/__init__.py
base_service/utils/common.py
base_service-0.1.0.dist-info/METADATA
base_service-0.1.0.dist-info/WHEEL
base_service-0.1.0.dist-info/top_level.txt
base_service-0.1.0.dist-info/RECORD
