Metadata-Version: 2.1
Name: base-service
Version: 0.1.0
Summary: Base service for common functionalities
Requires-Dist: fastapi
Requires-Dist: sqlalchemy
Requires-Dist: psycopg2-binary
